sphinx_theme_material/__init__.py
sphinx_theme_material/layout.html
sphinx_theme_material/search.html
sphinx_theme_material/theme.conf
sphinx_theme_material/static/bundle.css
sphinx_theme_material/static/bundle.js
sphinx_theme_material-1.1.2.dist-info/LICENSE
sphinx_theme_material-1.1.2.dist-info/METADATA
sphinx_theme_material-1.1.2.dist-info/WHEEL
sphinx_theme_material-1.1.2.dist-info/entry_points.txt
sphinx_theme_material-1.1.2.dist-info/top_level.txt
sphinx_theme_material-1.1.2.dist-info/RECORD
