Metadata-Version: 2.1
Name: sphinx-theme-material
Version: 1.1.2
Summary: A material based sphinx theme
Home-page: https://github.com/m-alzam/sphinx_theme_material
Author: Manuel Alcaraz Zambrano
License: GPLv3+
Keywords: sphinx theme
Platform: UNKNOWN
Classifier: Development Status :: 4 - Beta
Classifier: Framework :: Sphinx
Classifier: Framework :: Sphinx :: Theme
Classifier: Intended Audience :: Developers
Classifier: License :: OSI Approved :: GNU General Public License v3 or later (GPLv3+)
Classifier: Operating System :: OS Independent
Classifier: Topic :: Internet
Classifier: Topic :: Software Development :: Documentation
